LICENSE
MANIFEST.in
README.md
setup.py
charlotte_traffic_analysis.egg-info/PKG-INFO
charlotte_traffic_analysis.egg-info/SOURCES.txt
charlotte_traffic_analysis.egg-info/dependency_links.txt
charlotte_traffic_analysis.egg-info/not-zip-safe
charlotte_traffic_analysis.egg-info/requires.txt
charlotte_traffic_analysis.egg-info/top_level.txt
cmpd_accidents/__init__.py
cmpd_accidents/cmpd_service.py
cmpd_accidents/database.py
cmpd_accidents/logger.py
cmpd_accidents/main.py
cmpd_accidents/rest_service.py
cmpd_accidents/soap_service.py
cmpd_accidents/soup_service.py
cmpd_accidents/utility.py
cmpd_accidents/weather_service.py
cmpd_accidents/resources/db/mysql_create_accidents.sql
cmpd_accidents/resources/soap_descriptors/cmpd_soap_descriptor.xml
traffic_analyzer/__init__.py
traffic_analyzer/features.py
traffic_analyzer/logger.py
traffic_analyzer/main.py
traffic_analyzer/ml_functions.py
traffic_analyzer/model.py
traffic_analyzer/preprocess.py
traffic_analyzer/utility.py
traffic_analyzer/resources/models/xgb_cv_optimal.joblib
traffic_analyzer/resources/reference_data/census_income.csv
traffic_analyzer/resources/reference_data/census_population.csv
traffic_analyzer/resources/reference_data/roads.csv
traffic_analyzer/resources/reference_data/signals.csv
traffic_analyzer/resources/reference_data/traffic_volumes.csv