Metadata-Version: 1.0
Name: charlotte-traffic-analysis
Version: 0.1.2
Summary: Charlotte-metro traffic analysis helper including predictions, travel paths, and more
Home-page: UNKNOWN
Author: Dillon Mabry
Author-email: rapid.dev.solutions@gmail.com
License: MIT
Platform: UNKNOWN
